pytfc/__init__.py
pytfc/exceptions.py
pytfc/requestor.py
pytfc/tfc_api_base.py
pytfc/utils.py
pytfc/admin_api/__init__.py
pytfc/admin_api/admin_organizations.py
pytfc/admin_api/admin_runs.py
pytfc/admin_api/admin_settings.py
pytfc/admin_api/admin_terraform_versions.py
pytfc/admin_api/admin_users.py
pytfc/admin_api/admin_workspaces.py
pytfc/api/__init__.py
pytfc/api/agent_pools.py
pytfc/api/applies.py
pytfc/api/audit_trails.py
pytfc/api/configuration_versions.py
pytfc/api/notification_configurations.py
pytfc/api/oauth_clients.py
pytfc/api/oauth_tokens.py
pytfc/api/organizations.py
pytfc/api/plan_exports.py
pytfc/api/plans.py
pytfc/api/policy_checks.py
pytfc/api/projects.py
pytfc/api/registry_modules.py
pytfc/api/run_task_stages.py
pytfc/api/run_tasks.py
pytfc/api/run_triggers.py
pytfc/api/runs.py
pytfc/api/ssh_keys.py
pytfc/api/state_version_outputs.py
pytfc/api/state_versions.py
pytfc/api/team_access.py
pytfc/api/team_membership.py
pytfc/api/team_tokens.py
pytfc/api/teams.py
pytfc/api/variable_sets.py
pytfc/api/workspace_resources.py
pytfc/api/workspace_variables.py
pytfc/api/workspaces.py
tests/__init__.py
tests/conftest.py
tests/runs_test.py
tests/state_version_outputs_test.py
tests/variable_sets_test.py
tests/workspaces_test.py
pytfc-0.0.23.dist-info/LICENSE
pytfc-0.0.23.dist-info/METADATA
pytfc-0.0.23.dist-info/WHEEL
pytfc-0.0.23.dist-info/top_level.txt
pytfc-0.0.23.dist-info/RECORD
