Metadata-Version: 2.1
Name: pytfc
Version: 0.0.23
Summary: Python HTTP client library for Terraform Cloud/Enterprise API.
Home-page: https://github.com/alexbasista/pytfc
Author: Alex Basista
Author-email: alex.basista@gmail.com
Keywords: tfe,terraform enterprise,tfc,terraform cloud,terraform
Classifier: Development Status :: 3 - Alpha
Classifier: Programming Language :: Python :: 3
Classifier: License :: OSI Approved :: Mozilla Public License 2.0 (MPL 2.0)
Classifier: Operating System :: OS Independent
License-File: LICENSE
Requires-Dist: requests >=2.31.0
Requires-Dist: pyhcl >=0.4.4
Provides-Extra: dev
Requires-Dist: build ==1.0.3 ; extra == 'dev'
Requires-Dist: pytest ==7.4.2 ; extra == 'dev'
